act/__init__.py
act/actfile_parser.py
act/execution_manager.py
act/execution_setup.py
act/lint.py
act/node_context.py
act/workflow_engine.py
act/act/__init__.py
act/act/nodes/__init__.py
act/act/nodes/base_node.py
act/act/nodes/if_node.py
act/act/nodes/log_message_node.py
act/nodes/AggregateNode.py
act/nodes/ClaudeNode.py
act/nodes/DataformatterNode.py
act/nodes/DynamodbNode.py
act/nodes/FikenNode.py
act/nodes/FilterNode.py
act/nodes/GenericNode.py
act/nodes/GitHubNode.py
act/nodes/GitHubNodetest.py
act/nodes/IfNode.py
act/nodes/ListNode.py
act/nodes/LogMessageNode.py
act/nodes/Neo4jNode.py
act/nodes/OpenaiNode.py
act/nodes/RequestNode.py
act/nodes/SlackNode.py
act/nodes/StartNode.py
act/nodes/__init__.py
act/nodes/aci_node.py
act/nodes/base_node.py
act/nodes/data_node.py
act/nodes/gemini_node.py
act/nodes/generate_uuid_node.py
act/nodes/node_api.py
act/nodes/node_registry.py
act/nodes/set_node.py
act/nodes/switch_node.py
act/nodes/test_openai_node.py
act_workflow-4.8.399.dist-info/METADATA
act_workflow-4.8.399.dist-info/WHEEL
act_workflow-4.8.399.dist-info/entry_points.txt
act_workflow-4.8.399.dist-info/top_level.txt
act_workflow-4.8.399.dist-info/RECORD
